LICENSE
MANIFEST.in
README.md
setup.py
basic_oauth/__init__.py
basic_oauth/basic_oauth.py
basic_oauth.egg-info/PKG-INFO
basic_oauth.egg-info/SOURCES.txt
basic_oauth.egg-info/dependency_links.txt
basic_oauth.egg-info/requires.txt
basic_oauth.egg-info/top_level.txt