Metadata-Version: 1.0
Name: basic-oauth
Version: 0.1.1
Summary: Implements the "Resource Owner Password Credentials Grant" from Oauth v2.
Home-page: http://github.com/samalba/basic_oauth
Author: Sam Alba
Author-email: sam.alba@gmail.com
License: Copyright (c) 2012 Samuel Alba <sam.alba@gmail.com>
